marcxml2csv/__init__.py
marcxml2csv-1.1.1.dist-info/METADATA
marcxml2csv-1.1.1.dist-info/WHEEL
marcxml2csv-1.1.1.dist-info/entry_points.txt
marcxml2csv-1.1.1.dist-info/RECORD
